zeekr_ev_api/__init__.py
zeekr_ev_api/client.py
zeekr_ev_api/const.py
zeekr_ev_api/network.py
zeekr_ev_api/zeekr_app_sig.py
zeekr_ev_api/zeekr_hmac.py
zeekr_ev_api-0.1.8.dist-info/METADATA
zeekr_ev_api-0.1.8.dist-info/WHEEL
zeekr_ev_api-0.1.8.dist-info/licenses/LICENSE
zeekr_ev_api-0.1.8.dist-info/RECORD
