Metadata-Version: 2.4
Name: zeekr_ev_api
Version: 0.1.8
Summary: 
License-File: LICENSE
Author: Fry
Author-email: fryx0r@gmail.com
Requires-Python: >=3.10
Classifier: Programming Language :: Python :: 3
Classifier: Programming Language :: Python :: 3.10
Classifier: Programming Language :: Python :: 3.11
Classifier: Programming Language :: Python :: 3.12
Classifier: Programming Language :: Python :: 3.13
Classifier: Programming Language :: Python :: 3.14
Requires-Dist: pycryptodome (>=3.23.0,<4.0.0)
Requires-Dist: requests (>=2.32.5,<3.0.0)
